scrapli_replay/__init__.py
scrapli_replay/exceptions.py
scrapli_replay/logging.py
scrapli_replay/py.typed
scrapli_replay/replay/__init__.py
scrapli_replay/replay/pytest_scrapli_replay.py
scrapli_replay/replay/replay.py
scrapli_replay/server/__init__.py
scrapli_replay/server/collector.py
scrapli_replay/server/server.py
scrapli_replay-2024.7.30.dist-info/LICENSE
scrapli_replay-2024.7.30.dist-info/METADATA
scrapli_replay-2024.7.30.dist-info/WHEEL
scrapli_replay-2024.7.30.dist-info/entry_points.txt
scrapli_replay-2024.7.30.dist-info/top_level.txt
scrapli_replay-2024.7.30.dist-info/RECORD
